product_kit/__init__.py
product_kit/cli.py
product_kit/scaffolder.py
product_kit/data/constitution.md
product_kit/data/.ai-providers/CLAUDE.md
product_kit/data/.ai-providers/GEMINI.md
product_kit/data/.ai-providers/copilot-instructions.md
product_kit/data/agents/README.md
product_kit/data/agents/productkit.brd.agent.md
product_kit/data/agents/productkit.clarify.agent.md
product_kit/data/agents/productkit.constitution.agent.md
product_kit/data/agents/productkit.epic.agent.md
product_kit/data/agents/productkit.prd.agent.md
product_kit/data/agents/productkit.timeline.agent.md
product_kit/data/agents/productkit.update-context.agent.md
product_kit/data/agents/productkit.update-inventory.agent.md
product_kit/data/agents/productkit.user-story.agent.md
product_kit/data/context/glossary.md
product_kit/data/context/market_research.md
product_kit/data/context/personas.md
product_kit/data/context/product-vision.md
product_kit/data/context/teams.md
product_kit/data/inventory/data-model.md
product_kit/data/inventory/feature-catalog.md
product_kit/data/inventory/product-map.md
product_kit/data/inventory/tech-constraints.md
product_kit/data/prompts/productkit.brd.prompt.md
product_kit/data/prompts/productkit.clarify.prompt.md
product_kit/data/prompts/productkit.constitution.prompt.md
product_kit/data/prompts/productkit.epic.prompt.md
product_kit/data/prompts/productkit.prd.prompt.md
product_kit/data/prompts/productkit.timeline.prompt.md
product_kit/data/prompts/productkit.update-context.prompt.md
product_kit/data/prompts/productkit.update-inventory.prompt.md
product_kit/data/prompts/productkit.user-story.prompt.md
product_kit/data/templates/brd_template.md
product_kit/data/templates/epic_template.md
product_kit/data/templates/prd_template.md
product_kit/data/templates/timeline_template.md
product_kit/data/templates/user_story_template.md
product_kit-1.0.17.dist-info/METADATA
product_kit-1.0.17.dist-info/WHEEL
product_kit-1.0.17.dist-info/entry_points.txt
product_kit-1.0.17.dist-info/RECORD
