Metadata-Version: 2.4
Name: product-kit
Version: 1.0.17
Summary: CLI to scaffold Product Kit framework for requirement-driven design
Project-URL: Homepage, https://github.com/haikal/product-kit
Project-URL: Documentation, https://github.com/haikal/product-kit#readme
Project-URL: Repository, https://github.com/haikal/product-kit
Project-URL: Issues, https://github.com/haikal/product-kit/issues
Author-email: Haikal <farhienzahaikal@gmail.com>
License: MIT
Keywords: brd,copilot,prd,product-kit,product-management,rdd,requirements
Classifier: Development Status :: 4 - Beta
Classifier: Intended Audience :: Developers
Classifier: License :: OSI Approved :: MIT License
Classifier: Programming Language :: Python :: 3
Classifier: Programming Language :: Python :: 3.8
Classifier: Programming Language :: Python :: 3.9
Classifier: Programming Language :: Python :: 3.10
Classifier: Programming Language :: Python :: 3.11
Classifier: Programming Language :: Python :: 3.12
Requires-Python: >=3.8
Requires-Dist: rich>=13.7.0
Requires-Dist: typer>=0.12.0
Provides-Extra: dev
Requires-Dist: black>=24.0.0; extra == 'dev'
Requires-Dist: pytest>=8.0.0; extra == 'dev'
Requires-Dist: ruff>=0.3.0; extra == 'dev'
